apscli/JobNode.py
apscli/Xprocess.py
apscli/__init__.py
apscli/apscli.py
apscli/constant.py
apscli/controller.py
apscli/log.py
apscli/my_token.py
apscli/version.py
apscli/util/__init__.py
apscli/util/aps_jobcontrol.py
apscli/util/lock.py
apscli/util/mq.py
apscli/util/sqlite_wrapper.py
apscli/util/url.py
apscli/util/wf_build.py
apscli/util/wf_runtime.py
apscli-0.1.9.18.dist-info/DESCRIPTION.rst
apscli-0.1.9.18.dist-info/LICENSE.txt
apscli-0.1.9.18.dist-info/METADATA
apscli-0.1.9.18.dist-info/RECORD
apscli-0.1.9.18.dist-info/WHEEL
apscli-0.1.9.18.dist-info/metadata.json
apscli-0.1.9.18.dist-info/top_level.txt
apscli-0.1.9.18.dist-info/zip-safe
