Metadata-Version: 2.0
Name: apscli
Version: 0.1.9.18
Summary: A general purpose workflow engine & orchestration tool with service_management functionality, written in Python
Home-page: https://github.com/oracle/apscli
Author: Oracle
Author-email: huayang.jiang@oracle.com
License: dual-licensed, under the Universal Permissive License (UPL) and Apache License 2.0
Platform: UNKNOWN
Classifier: Development Status :: 5 - Production/Stable
Classifier: Intended Audience :: Developers
Classifier: License :: OSI Approved :: Apache Software License
Classifier: Operating System :: MacOS
Classifier: Operating System :: Microsoft
Classifier: Operating System :: POSIX
Classifier: Operating System :: Unix
Classifier: Programming Language :: Python :: 2.7
Classifier: Programming Language :: Python :: 3.5
Classifier: Programming Language :: Python :: 3.6
Classifier: Topic :: Software Development :: Libraries :: Python Modules
Requires-Dist: python-dateutil
Requires-Dist: six (>=1.11.0)
